{
    "DATE": {
        "prefix": [
            {
                "pattern": "約",
                "mod": "APPROX"
            },
            {
                "pattern": "だいたい",
                "mod": "APPROX"
            },
            {
                "pattern": "ほぼ",
                "mod": "APPROX"
            },
            {
                "pattern": "おおよそ",
                "mod": "APPROX"
            },
            {
                "pattern": "殆ど",
                "mod": "APPROX"
            },
            {
                "pattern": "ほとんど",
                "mod": "APPROX"
            }
        ],
        "suffix": [
            {
                "pattern": "頃",
                "mod": "APPROX"
            },
            {
                "pattern": "ごろ",
                "mod": "APPROX"
            }
        ]
    },
    "DURATION": {
        "prefix": [            {
            "pattern": "約",
            "mod": "APPROX"
        }],
        "suffix": []
    },
    "TIME": {
        "prefix": [],
        "suffix": []
    },
    "SET": {
        "prefix": [],
        "suffix": []
    }
}